MILESTONE 2/interval_min_max.v
`timescale 1ns / 1ps

module audio_min_max_interval (
    input wire reset,
    input wire start,
    input wire clk,
    input reg [31:0] raw_audio [N-1:0],  // raw audio data
    input reg [15:0] interval_len,  // interval length
    output reg done,
    output reg signed [31:0] out_max [NUM_INTERVALS-1:0],  // max audio amplitude per interval
    output reg signed [31:0] out_min [NUM_INTERVALS-1:0]   // min audio amplitude per interval
);

localparam IDLE = 0;
localparam INTERVAL_START = 1;
localparam INTERVAL_COMPUTING = 2;
localparam INTERVAL_DONE = 3;
localparam N = 100;  // number of samples
localparam NUM_INTERVALS = N / 10;  // number of intervals (assuming interval_len = 10)

reg [1:0] state;
reg signed [31:0] max;
reg signed [31:0] min;
reg signed [31:0] y;  // sample placeholder
reg [15:0] interval_counter;
reg [6:0] interval_index;

integer i = 0;

always @(posedge clk) begin
    if (reset) begin
        done <= 0;
        state <= IDLE;
        interval_index <= 0;
    end else begin
        case (state)
            IDLE: begin
                i <= 0;
                if (start) begin
                    state <= INTERVAL_START;
                end
            end
            INTERVAL_START: begin
                
                min <= 32'h7FFFFFFF; // set min to highest signed int
                max <= 32'h80000000; // set max to lowest signed int
                interval_counter <= 0;
                state <= INTERVAL_COMPUTING;
            end
            INTERVAL_COMPUTING: begin
                
                y = raw_audio[i];
                if (y < min) begin
                    min <= y;
                end
                if (y > max) begin
                    max <= y;
                end
                i <= i + 1;
                interval_counter <= interval_counter + 1;
                if (interval_counter == interval_len - 1) begin
                    state <= INTERVAL_DONE;
                end
            end
            INTERVAL_DONE: begin
                out_max[interval_index] <= max;
                out_min[interval_index] <= min;
                interval_index <= interval_index + 1;
                if (i > N - 1) begin
                    state <= IDLE;
                    done <= 1;
                end else begin
                    state <= INTERVAL_START;
                end
            end
        endcase
    end
end

endmodule

MILESTONE 2/interval_min_max_tb.v
`timescale 1ns / 1ps

module audio_min_max_tb;
localparam N = 100; // Number of samples
localparam NUM_INTERVALS = N/10;

reg reset, start, clk;
reg signed [31:0] raw_audio [N-1:0];
wire done;
wire signed [31:0] out_max [NUM_INTERVALS-1:0], out_min [NUM_INTERVALS-1:0];
reg [15:0] interval_len;
// Instantiate audio_min_max_interval
audio_min_max_interval aud_minmaxint (
    .reset(reset),
    .start(start),
    .clk(clk),
    .raw_audio(raw_audio),
    .done(done),
    .interval_len(interval_len),
    .out_max(out_max),
    .out_min(out_min)
);
// Clock generation
always #5 clk = ~clk;
integer i = 0;
// Test case: Hardcoded array from CSV file
initial begin
    clk = 0;
    reset = 1;
    start = 0;
    interval_len = 10;
    // Load the hardcoded array
    raw_audio[0] = 196608;
    raw_audio[1] = 458752;
    raw_audio[2] = 0;
    raw_audio[3] = 327680;
    raw_audio[4] = 458752;
    raw_audio[5] = 262144;
    raw_audio[6] = 196608;
    raw_audio[7] = 458752;
    raw_audio[8] = 327680;
    raw_audio[9] = 327680;
    raw_audio[10] = 131072;
    raw_audio[11] = 196608;
    raw_audio[12] = -65536;
    raw_audio[13] = 0;
    raw_audio[14] = 262144;
    raw_audio[15] = 131072;
    raw_audio[16] = -131072;
    raw_audio[17] = -65536;
    raw_audio[18] = 65536;
    raw_audio[19] = 65536;
    raw_audio[20] = 65536;
    raw_audio[21] = -131072;
    raw_audio[22] = -131072;
    raw_audio[23] = 65536;
    raw_audio[24] = 131072;
    raw_audio[25] = -262144;
    raw_audio[26] = -262144;
    raw_audio[27] = 0;
    raw_audio[28] = -131072;
    raw_audio[29] = -196608;
    raw_audio[30] = -131072;
    raw_audio[31] = -65536;
    raw_audio[32] = -196608;
    raw_audio[33] = -393216;
    raw_audio[34] = -458752;
    raw_audio[35] = -327680;
    raw_audio[36] = -196608;
    raw_audio[37] = -196608;
    raw_audio[38] = -327680;
    raw_audio[39] = -262144;
    raw_audio[40] = -524288;
    raw_audio[41] = -327680;
    raw_audio[42] = -589824;
    raw_audio[43] = -524288;
    raw_audio[44] = -524288;
    raw_audio[45] = -393216;
    raw_audio[46] = -589824;
    raw_audio[47] = -720896;
    raw_audio[48] = -851968;
    raw_audio[49] = -720896;
    raw_audio[50] = -786432;
    raw_audio[51] = -720896;
    raw_audio[52] = -786432;
    raw_audio[53] = -786432;
    raw_audio[54] = -655360;
    raw_audio[55] = -720896;
    raw_audio[56] = -851968;
    raw_audio[57] = -917504;
    raw_audio[58] = -589824;
    raw_audio[59] = -851968;
    raw_audio[60] = -589824;
    raw_audio[61] = -589824;
    raw_audio[62] = -786432;
    raw_audio[63] = -1048576;
    raw_audio[64] = -917504;
    raw_audio[65] = -1245184;
    raw_audio[66] = -983040;
    raw_audio[67] = -1048576;
    raw_audio[68] = -851968;
    raw_audio[69] = -1048576;
    raw_audio[70] = -983040;
    raw_audio[71] = -1048576;
    raw_audio[72] = -1048576;
    raw_audio[73] = -917504;
    raw_audio[74] = -917504;
    raw_audio[75] = -1114112;
    raw_audio[76] = -1179648;
    raw_audio[77] = -917504;
    raw_audio[78] = -983040;
    raw_audio[79] = -1376256;
    raw_audio[80] = -1245184;
    raw_audio[81] = -983040;
    raw_audio[82] = -1245184;
    raw_audio[83] = -1179648;
    raw_audio[84] = -1310720;
    raw_audio[85] = -1114112;
    raw_audio[86] = -1245184;
    raw_audio[87] = -1245184;
    raw_audio[88] = -1441792;
    raw_audio[89] = -1245184;
    raw_audio[90] = -1245184;
    raw_audio[91] = -1376256;
    raw_audio[92] = -1441792;
    raw_audio[93] = -1507328;
    raw_audio[94] = -1310720;
    raw_audio[95] = -1507328;
    raw_audio[96] = -1441792;
    raw_audio[97] = -1769472;
    raw_audio[98] = -1376256;
    raw_audio[99] = -1441792;
    #10 reset = 0;
    #10 start = 1;
    #10 start = 0;
    // Wait for the computation to complete
    wait (done);
    // Print the results
    #5
    for (i= 0; i<NUM_INTERVALS; i=i+1) begin
        $display("%1d. Maximum: %1d, Minimum: %1d", i, out_max[i], out_min[i]);
    end
    $finish;
    
end
initial begin
    $dumpfile("dump.vcd");
    $dumpvars; 
end
endmodule

Vivado/eee4120f_yoda_spm.sim/sim_2/behav/xsim/dump.vcd
$date
   Mon May 13 20:58:52 2024
$end

$version
  2023.2
  $dumpfile ("dump.vcd") 
$end

$timescale
  1ps
$end

$scope module audio_min_max_tb $end
$var reg 1 ! reset $end
$var reg 1 " start $end
$var reg 1 # clk $end
$var wire 1 $ done $end
$var reg 16 % interval_len [15:0] $end
$var integer 32 & i [31:0] $end
$scope module aud_minmaxint $end
$var wire 1 ' reset $end
$var wire 1 ( start $end
$var wire 1 ) clk $end
$var reg 16 % interval_len [15:0] $end
$var reg 1 * done $end
$var reg 2 + state [1:0] $end
$var reg 32 , max [31:0] $end
$var reg 32 - min [31:0] $end
$var reg 32 . y [31:0] $end
$var reg 16 / interval_counter [15:0] $end
$var reg 7 0 interval_index [6:0] $end
$var integer 32 1 i [31:0] $end
$upscope $end
$upscope $end
$enddefinitions $end

#0
$dumpvars
1!
0"
0#
x$
b1010 %
b0 &
1'
0(
0)
x*
bx +
bx ,
bx -
bx .
bx /
bx 0
b0 1
$end

#5000
1#
0$
1)
0*
b0 +
b0 0

#10000
0!
0#
0'
0)

#15000
1#
1)

#20000
1"
0#
1(
0)

#25000
1#
1)
b1 +

#30000
0"
0#
0(
0)

#35000
1#
1)
b10 +
b110000000000000000 ,
b110000000000000000 -
b0 /

#40000
0#
0)

#45000
1#
1)
b110000000000000000 .
b1 /
b1 1

#50000
0#
0)

#55000
1#
1)
b1110000000000000000 ,
b1110000000000000000 .
b10 /
b10 1

#60000
0#
0)

#65000
1#
1)
b0 -
b0 .
b11 /
b11 1

#70000
0#
0)

#75000
1#
1)
b1010000000000000000 .
b100 /
b100 1

#80000
0#
0)

#85000
1#
1)
b1110000000000000000 .
b101 /
b101 1

#90000
0#
0)

#95000
1#
1)
b1000000000000000000 .
b110 /
b110 1

#100000
0#
0)

#105000
1#
1)
b110000000000000000 .
b111 /
b111 1

#110000
0#
0)

#115000
1#
1)
b1110000000000000000 .
b1000 /
b1000 1

#120000
0#
0)

#125000
1#
1)
b1010000000000000000 .
b1001 /
b1001 1

#130000
0#
0)

#135000
1#
1)
b11 +
b1010 /
b1010 1

#140000
0#
0)

#145000
1#
1)
b1 +
b1 0

#150000
0#
0)

#155000
1#
1)
b10 +
b100000000000000000 ,
b100000000000000000 -
b0 /

#160000
0#
0)

#165000
1#
1)
b100000000000000000 .
b1 /
b1011 1

#170000
0#
0)

#175000
1#
1)
b110000000000000000 ,
b110000000000000000 .
b10 /
b1100 1

#180000
0#
0)

#185000
1#
1)
b11111111111111110000000000000000 -
b11111111111111110000000000000000 .
b11 /
b1101 1

#190000
0#
0)

#195000
1#
1)
b0 .
b100 /
b1110 1

#200000
0#
0)

#205000
1#
1)
b1000000000000000000 ,
b1000000000000000000 .
b101 /
b1111 1

#210000
0#
0)

#215000
1#
1)
b100000000000000000 .
b110 /
b10000 1

#220000
0#
0)

#225000
1#
1)
b11111111111111100000000000000000 -
b11111111111111100000000000000000 .
b111 /
b10001 1

#230000
0#
0)

#235000
1#
1)
b11111111111111110000000000000000 .
b1000 /
b10010 1

#240000
0#
0)

#245000
1#
1)
b10000000000000000 .
b1001 /
b10011 1

#250000
0#
0)

#255000
1#
1)
b11 +
b1010 /
b10100 1

#260000
0#
0)

#265000
1#
1)
b1 +
b10 0

#270000
0#
0)

#275000
1#
1)
b10 +
b10000000000000000 ,
b10000000000000000 -
b0 /

#280000
0#
0)

#285000
1#
1)
b1 /
b10101 1

#290000
0#
0)

#295000
1#
1)
b11111111111111100000000000000000 -
b11111111111111100000000000000000 .
b10 /
b10110 1

#300000
0#
0)

#305000
1#
1)
b11 /
b10111 1

#310000
0#
0)

#315000
1#
1)
b10000000000000000 .
b100 /
b11000 1

#320000
0#
0)

#325000
1#
1)
b100000000000000000 ,
b100000000000000000 .
b101 /
b11001 1

#330000
0#
0)

#335000
1#
1)
b11111111111111000000000000000000 -
b11111111111111000000000000000000 .
b110 /
b11010 1

#340000
0#
0)

#345000
1#
1)
b111 /
b11011 1

#350000
0#
0)

#355000
1#
1)
b0 .
b1000 /
b11100 1

#360000
0#
0)

#365000
1#
1)
b11111111111111100000000000000000 .
b1001 /
b11101 1

#370000
0#
0)

#375000
1#
1)
b11 +
b11111111111111010000000000000000 .
b1010 /
b11110 1

#380000
0#
0)

#385000
1#
1)
b1 +
b11 0

#390000
0#
0)

#395000
1#
1)
b10 +
b11111111111111100000000000000000 ,
b11111111111111100000000000000000 -
b0 /

#400000
0#
0)

#405000
1#
1)
b11111111111111100000000000000000 .
b1 /
b11111 1

#410000
0#
0)

#415000
1#
1)
b11111111111111110000000000000000 ,
b11111111111111110000000000000000 .
b10 /
b100000 1

#420000
0#
0)

#425000
1#
1)
b11111111111111010000000000000000 -
b11111111111111010000000000000000 .
b11 /
b100001 1

#430000
0#
0)

#435000
1#
1)
b11111111111110100000000000000000 -
b11111111111110100000000000000000 .
b100 /
b100010 1

#440000
0#
0)

#445000
1#
1)
b11111111111110010000000000000000 -
b11111111111110010000000000000000 .
b101 /
b100011 1

#450000
0#
0)

#455000
1#
1)
b11111111111110110000000000000000 .
b110 /
b100100 1

#460000
0#
0)

#465000
1#
1)
b11111111111111010000000000000000 .
b111 /
b100101 1

#470000
0#
0)

#475000
1#
1)
b1000 /
b100110 1

#480000
0#
0)

#485000
1#
1)
b11111111111110110000000000000000 .
b1001 /
b100111 1

#490000
0#
0)

#495000
1#
1)
b11 +
b11111111111111000000000000000000 .
b1010 /
b101000 1

#500000
0#
0)

#505000
1#
1)
b1 +
b100 0

#510000
0#
0)

#515000
1#
1)
b10 +
b11111111111110000000000000000000 ,
b11111111111110000000000000000000 -
b0 /

#520000
0#
0)

#525000
1#
1)
b11111111111110000000000000000000 .
b1 /
b101001 1

#530000
0#
0)

#535000
1#
1)
b11111111111110110000000000000000 ,
b11111111111110110000000000000000 .
b10 /
b101010 1

#540000
0#
0)

#545000
1#
1)
b11111111111101110000000000000000 -
b11111111111101110000000000000000 .
b11 /
b101011 1

#550000
0#
0)

#555000
1#
1)
b11111111111110000000000000000000 .
b100 /
b101100 1

#560000
0#
0)

#565000
1#
1)
b101 /
b101101 1

#570000
0#
0)

#575000
1#
1)
b11111111111110100000000000000000 .
b110 /
b101110 1

#580000
0#
0)

#585000
1#
1)
b11111111111101110000000000000000 .
b111 /
b101111 1

#590000
0#
0)

#595000
1#
1)
b11111111111101010000000000000000 -
b11111111111101010000000000000000 .
b1000 /
b110000 1

#600000
0#
0)

#605000
1#
1)
b11111111111100110000000000000000 -
b11111111111100110000000000000000 .
b1001 /
b110001 1

#610000
0#
0)

#615000
1#
1)
b11 +
b11111111111101010000000000000000 .
b1010 /
b110010 1

#620000
0#
0)

#625000
1#
1)
b1 +
b101 0

#630000
0#
0)

#635000
1#
1)
b10 +
b11111111111101000000000000000000 ,
b11111111111101000000000000000000 -
b0 /

#640000
0#
0)

#645000
1#
1)
b11111111111101000000000000000000 .
b1 /
b110011 1

#650000
0#
0)

#655000
1#
1)
b11111111111101010000000000000000 ,
b11111111111101010000000000000000 .
b10 /
b110100 1

#660000
0#
0)

#665000
1#
1)
b11111111111101000000000000000000 .
b11 /
b110101 1

#670000
0#
0)

#675000
1#
1)
b100 /
b110110 1

#680000
0#
0)

#685000
1#
1)
b11111111111101100000000000000000 ,
b11111111111101100000000000000000 .
b101 /
b110111 1

#690000
0#
0)

#695000
1#
1)
b11111111111101010000000000000000 .
b110 /
b111000 1

#700000
0#
0)

#705000
1#
1)
b11111111111100110000000000000000 -
b11111111111100110000000000000000 .
b111 /
b111001 1

#710000
0#
0)

#715000
1#
1)
b11111111111100100000000000000000 -
b11111111111100100000000000000000 .
b1000 /
b111010 1

#720000
0#
0)

#725000
1#
1)
b11111111111101110000000000000000 ,
b11111111111101110000000000000000 .
b1001 /
b111011 1

#730000
0#
0)

#735000
1#
1)
b11 +
b11111111111100110000000000000000 .
b1010 /
b111100 1

#740000
0#
0)

#745000
1#
1)
b1 +
b110 0

#750000
0#
0)

#755000
1#
1)
b10 +
b11111111111101110000000000000000 -
b0 /

#760000
0#
0)

#765000
1#
1)
b11111111111101110000000000000000 .
b1 /
b111101 1

#770000
0#
0)

#775000
1#
1)
b10 /
b111110 1

#780000
0#
0)

#785000
1#
1)
b11111111111101000000000000000000 -
b11111111111101000000000000000000 .
b11 /
b111111 1

#790000
0#
0)

#795000
1#
1)
b11111111111100000000000000000000 -
b11111111111100000000000000000000 .
b100 /
b1000000 1

#800000
0#
0)

#805000
1#
1)
b11111111111100100000000000000000 .
b101 /
b1000001 1

#810000
0#
0)

#815000
1#
1)
b11111111111011010000000000000000 -
b11111111111011010000000000000000 .
b110 /
b1000010 1

#820000
0#
0)

#825000
1#
1)
b11111111111100010000000000000000 .
b111 /
b1000011 1

#830000
0#
0)

#835000
1#
1)
b11111111111100000000000000000000 .
b1000 /
b1000100 1

#840000
0#
0)

#845000
1#
1)
b11111111111100110000000000000000 .
b1001 /
b1000101 1

#850000
0#
0)

#855000
1#
1)
b11 +
b11111111111100000000000000000000 .
b1010 /
b1000110 1

#860000
0#
0)

#865000
1#
1)
b1 +
b111 0

#870000
0#
0)

#875000
1#
1)
b10 +
b11111111111100010000000000000000 ,
b11111111111100010000000000000000 -
b0 /

#880000
0#
0)

#885000
1#
1)
b11111111111100010000000000000000 .
b1 /
b1000111 1

#890000
0#
0)

#895000
1#
1)
b11111111111100000000000000000000 -
b11111111111100000000000000000000 .
b10 /
b1001000 1

#900000
0#
0)

#905000
1#
1)
b11 /
b1001001 1

#910000
0#
0)

#915000
1#
1)
b11111111111100100000000000000000 ,
b11111111111100100000000000000000 .
b100 /
b1001010 1

#920000
0#
0)

#925000
1#
1)
b101 /
b1001011 1

#930000
0#
0)

#935000
1#
1)
b11111111111011110000000000000000 -
b11111111111011110000000000000000 .
b110 /
b1001100 1

#940000
0#
0)

#945000
1#
1)
b11111111111011100000000000000000 -
b11111111111011100000000000000000 .
b111 /
b1001101 1

#950000
0#
0)

#955000
1#
1)
b11111111111100100000000000000000 .
b1000 /
b1001110 1

#960000
0#
0)

#965000
1#
1)
b11111111111100010000000000000000 .
b1001 /
b1001111 1

#970000
0#
0)

#975000
1#
1)
b11 +
b11111111111010110000000000000000 -
b11111111111010110000000000000000 .
b1010 /
b1010000 1

#980000
0#
0)

#985000
1#
1)
b1 +
b1000 0

#990000
0#
0)

#995000
1#
1)
b10 +
b11111111111011010000000000000000 ,
b11111111111011010000000000000000 -
b0 /

#1000000
0#
0)

#1005000
1#
1)
b11111111111011010000000000000000 .
b1 /
b1010001 1

#1010000
0#
0)

#1015000
1#
1)
b11111111111100010000000000000000 ,
b11111111111100010000000000000000 .
b10 /
b1010010 1

#1020000
0#
0)

#1025000
1#
1)
b11111111111011010000000000000000 .
b11 /
b1010011 1

#1030000
0#
0)

#1035000
1#
1)
b11111111111011100000000000000000 .
b100 /
b1010100 1

#1040000
0#
0)

#1045000
1#
1)
b11111111111011000000000000000000 -
b11111111111011000000000000000000 .
b101 /
b1010101 1

#1050000
0#
0)

#1055000
1#
1)
b11111111111011110000000000000000 .
b110 /
b1010110 1

#1060000
0#
0)

#1065000
1#
1)
b11111111111011010000000000000000 .
b111 /
b1010111 1

#1070000
0#
0)

#1075000
1#
1)
b1000 /
b1011000 1

#1080000
0#
0)

#1085000
1#
1)
b11111111111010100000000000000000 -
b11111111111010100000000000000000 .
b1001 /
b1011001 1

#1090000
0#
0)

#1095000
1#
1)
b11 +
b11111111111011010000000000000000 .
b1010 /
b1011010 1

#1100000
0#
0)

#1105000
1#
1)
b1 +
b1001 0

#1110000
0#
0)

#1115000
1#
1)
b10 +
b11111111111011010000000000000000 ,
b11111111111011010000000000000000 -
b0 /

#1120000
0#
0)

#1125000
1#
1)
b1 /
b1011011 1

#1130000
0#
0)

#1135000
1#
1)
b11111111111010110000000000000000 -
b11111111111010110000000000000000 .
b10 /
b1011100 1

#1140000
0#
0)

#1145000
1#
1)
b11111111111010100000000000000000 -
b11111111111010100000000000000000 .
b11 /
b1011101 1

#1150000
0#
0)

#1155000
1#
1)
b11111111111010010000000000000000 -
b11111111111010010000000000000000 .
b100 /
b1011110 1

#1160000
0#
0)

#1165000
1#
1)
b11111111111011000000000000000000 .
b101 /
b1011111 1

#1170000
0#
0)

#1175000
1#
1)
b11111111111010010000000000000000 .
b110 /
b1100000 1

#1180000
0#
0)

#1185000
1#
1)
b11111111111010100000000000000000 .
b111 /
b1100001 1

#1190000
0#
0)

#1195000
1#
1)
b11111111111001010000000000000000 -
b11111111111001010000000000000000 .
b1000 /
b1100010 1

#1200000
0#
0)

#1205000
1#
1)
b11111111111010110000000000000000 .
b1001 /
b1100011 1

#1210000
0#
0)

#1215000
1#
1)
b11 +
b11111111111010100000000000000000 .
b1010 /
b1100100 1

#1220000
0#
0)

#1225000
1#
1$
1)
1*
b0 +
b1010 0
