MILESTONE 2/basic_min_max.v
module audio_min_max (
    input wire reset,  // reset when high
    input wire start,  // start pulse
    input wire clk,    // clock
    input reg signed [31:0] raw_audio [N-1:0], // raw audio data
    output reg d,      // done computing min & max
    output reg signed [31:0] out_max, // max audio amplitude
    output reg signed [31:0] out_min // min audio amplitude
);

localparam IDLE = 2'b00;
localparam COMPUTING = 2'b01;
localparam N = 100; // Number of samples 

reg [1:0] state;          // state
reg signed [31:0] max;    // current max
reg signed [31:0] min;    // current min
reg signed [31:0] y;      // sample placeholder

integer i = 0;

always @(posedge clk) begin
    if (reset) begin
        d <= 0;
        min <= 32'h7FFFFFFF; // maximum positive value for a 32-bit signed integer
        max <= 32'h80000000; // maximum negative value for a 32-bit signed integer
        state <= IDLE;
    end else begin
        case (state)
            IDLE: begin
                if (start) begin
                    state <= COMPUTING;
                    i <= 0; // Reset loop counter
                    min <= 32'h7FFFFFFF;; // Set initial min value to the first sample
                    max <= -32'h80000000; // Set initial max value to the first sample
                end
            end
           COMPUTING: begin
                y = raw_audio[i];
                if (y < min) begin
                    min <= y;
                    $display("Min now is: %d", min);
                end 
                if (y > max) begin
                    max <= y;
                    $display("Max now is: %d", max);
                end
                i = i + 1;

                if (i == N) begin
                    out_max <= max;
                    out_min <= min;
                    state <= IDLE;
                    d <= 1;
                end
            end

        endcase
    end
end

endmodule

MILESTONE 2/basic_min_max_csv_tb.v

module audio_min_max_tb;
localparam N = 100; // Number of samples
reg reset, start, clk;
reg signed [31:0] raw_audio [N-1:0];
wire d;
wire signed [31:0] out_max, out_min;
// Instantiate audio_min_max
audio_min_max aud_minmax (
    .reset(reset),
    .start(start),
    .clk(clk),
    .raw_audio(raw_audio),
    .d(d),
    .out_max(out_max),
    .out_min(out_min)
);
// Clock generation
always #5 clk = ~clk;
// Test case: Hardcoded array from CSV file
initial begin
    clk = 0;
    reset = 1;
    start = 0;
    // Load the hardcoded array
    raw_audio[0] = 0;
    raw_audio[1] = 0;
    raw_audio[2] = 0;
    raw_audio[3] = 0;
    raw_audio[4] = 0;
    raw_audio[5] = 0;
    raw_audio[6] = 0;
    raw_audio[7] = 0;
    raw_audio[8] = 0;
    raw_audio[9] = 0;
    raw_audio[10] = 0;
    raw_audio[11] = 0;
    raw_audio[12] = 0;
    raw_audio[13] = 0;
    raw_audio[14] = 0;
    raw_audio[15] = 0;
    raw_audio[16] = 0;
    raw_audio[17] = 0;
    raw_audio[18] = 0;
    raw_audio[19] = 0;
    raw_audio[20] = 0;
    raw_audio[21] = 0;
    raw_audio[22] = 0;
    raw_audio[23] = 0;
    raw_audio[24] = 0;
    raw_audio[25] = 0;
    raw_audio[26] = 0;
    raw_audio[27] = 0;
    raw_audio[28] = 0;
    raw_audio[29] = 0;
    raw_audio[30] = 0;
    raw_audio[31] = 0;
    raw_audio[32] = 0;
    raw_audio[33] = 0;
    raw_audio[34] = 0;
    raw_audio[35] = 0;
    raw_audio[36] = 0;
    raw_audio[37] = 0;
    raw_audio[38] = 0;
    raw_audio[39] = 0;
    raw_audio[40] = 0;
    raw_audio[41] = 0;
    raw_audio[42] = 0;
    raw_audio[43] = 0;
    raw_audio[44] = 0;
    raw_audio[45] = 0;
    raw_audio[46] = 0;
    raw_audio[47] = 0;
    raw_audio[48] = 0;
    raw_audio[49] = 0;
    raw_audio[50] = 0;
    raw_audio[51] = 0;
    raw_audio[52] = 0;
    raw_audio[53] = 0;
    raw_audio[54] = 0;
    raw_audio[55] = 0;
    raw_audio[56] = 0;
    raw_audio[57] = 0;
    raw_audio[58] = 0;
    raw_audio[59] = 0;
    raw_audio[60] = 0;
    raw_audio[61] = 0;
    raw_audio[62] = 0;
    raw_audio[63] = 0;
    raw_audio[64] = 0;
    raw_audio[65] = 0;
    raw_audio[66] = 0;
    raw_audio[67] = 0;
    raw_audio[68] = 0;
    raw_audio[69] = 0;
    raw_audio[70] = 0;
    raw_audio[71] = 0;
    raw_audio[72] = 0;
    raw_audio[73] = 0;
    raw_audio[74] = 0;
    raw_audio[75] = 0;
    raw_audio[76] = 0;
    raw_audio[77] = 0;
    raw_audio[78] = 0;
    raw_audio[79] = 0;
    raw_audio[80] = 0;
    raw_audio[81] = 0;
    raw_audio[82] = 0;
    raw_audio[83] = 0;
    raw_audio[84] = 0;
    raw_audio[85] = 0;
    raw_audio[86] = 0;
    raw_audio[87] = 0;
    raw_audio[88] = 0;
    raw_audio[89] = 0;
    raw_audio[90] = 0;
    raw_audio[91] = 0;
    raw_audio[92] = 0;
    raw_audio[93] = 0;
    raw_audio[94] = 0;
    raw_audio[95] = 0;
    raw_audio[96] = 0;
    raw_audio[97] = 0;
    raw_audio[98] = 0;
    raw_audio[99] = 0;
    #10 reset = 0;
    #10 start = 1;
    #10 start = 0;
    // Wait for the computation to complete
    wait (d);
    // Print the results
    $display("Maximum: %d, Minimum: %d", out_max, out_min);
end
endmodule

Vivado/eee4120f_yoda_spm.sim/sim_1/behav/xsim/dump.vcd
$date
   Mon May 13 09:37:19 2024
$end

$version
  2023.2
  $dumpfile ("dump.vcd") 
$end

$timescale
  1ps
$end

$scope module audio_min_max_tb $end
$var reg 1 ! reset $end
$var reg 1 " start $end
$var reg 1 # clk $end
$var wire 1 $ d $end
$var wire 32 % out_max [31:0] $end
$var wire 32 & out_min [31:0] $end
$scope module aud_minmax $end
$var wire 1 ' reset $end
$var wire 1 ( start $end
$var wire 1 ) clk $end
$var reg 1 * d $end
$var reg 32 + out_max [31:0] $end
$var reg 32 , out_min [31:0] $end
$var reg 2 - state [1:0] $end
$var reg 32 . max [31:0] $end
$var reg 32 / min [31:0] $end
$var reg 32 0 y [31:0] $end
$var integer 32 1 i [31:0] $end
$upscope $end
$upscope $end
$enddefinitions $end

#0
$dumpvars
1!
0"
0#
x$
bx %
bx &
1'
0(
0)
x*
bx +
bx ,
bx -
bx .
bx /
bx 0
b0 1
$end

#5000
1#
0$
1)
0*
b0 -
b10000000000000000000000000000000 .
b1111111111111111111111111111111 /

#10000
0!
0#
0'
0)

#15000
1#
1)

#20000
1"
0#
1(
0)

#25000
1#
1)
b1 -

#30000
0"
0#
0(
0)

#35000
1#
1)
b110000000000000000 .
b110000000000000000 /
b110000000000000000 0
b1 1

#40000
0#
0)

#45000
1#
1)
b1110000000000000000 .
b1110000000000000000 0
b10 1

#50000
0#
0)

#55000
1#
1)
b0 /
b0 0
b11 1

#60000
0#
0)

#65000
1#
1)
b1010000000000000000 0
b100 1

#70000
0#
0)

#75000
1#
1)
b1110000000000000000 0
b101 1

#80000
0#
0)

#85000
1#
1)
b1000000000000000000 0
b110 1

#90000
0#
0)

#95000
1#
1)
b110000000000000000 0
b111 1

#100000
0#
0)

#105000
1#
1)
b1110000000000000000 0
b1000 1

#110000
0#
0)

#115000
1#
1)
b1010000000000000000 0
b1001 1

#120000
0#
0)

#125000
1#
1)
b1010 1

#130000
0#
0)

#135000
1#
1)
b100000000000000000 0
b1011 1

#140000
0#
0)

#145000
1#
1)
b110000000000000000 0
b1100 1

#150000
0#
0)

#155000
1#
1)
b11111111111111110000000000000000 /
b11111111111111110000000000000000 0
b1101 1

#160000
0#
0)

#165000
1#
1)
b0 0
b1110 1

#170000
0#
0)

#175000
1#
1)
b1000000000000000000 0
b1111 1

#180000
0#
0)

#185000
1#
1)
b100000000000000000 0
b10000 1

#190000
0#
0)

#195000
1#
1)
b11111111111111100000000000000000 /
b11111111111111100000000000000000 0
b10001 1

#200000
0#
0)

#205000
1#
1)
b11111111111111110000000000000000 0
b10010 1

#210000
0#
0)

#215000
1#
1)
b10000000000000000 0
b10011 1

#220000
0#
0)

#225000
1#
1)
b10100 1

#230000
0#
0)

#235000
1#
1)
b10101 1

#240000
0#
0)

#245000
1#
1)
b11111111111111100000000000000000 0
b10110 1

#250000
0#
0)

#255000
1#
1)
b10111 1

#260000
0#
0)

#265000
1#
1)
b10000000000000000 0
b11000 1

#270000
0#
0)

#275000
1#
1)
b100000000000000000 0
b11001 1

#280000
0#
0)

#285000
1#
1)
b11111111111111000000000000000000 /
b11111111111111000000000000000000 0
b11010 1

#290000
0#
0)

#295000
1#
1)
b11011 1

#300000
0#
0)

#305000
1#
1)
b0 0
b11100 1

#310000
0#
0)

#315000
1#
1)
b11111111111111100000000000000000 0
b11101 1

#320000
0#
0)

#325000
1#
1)
b11111111111111010000000000000000 0
b11110 1

#330000
0#
0)

#335000
1#
1)
b11111111111111100000000000000000 0
b11111 1

#340000
0#
0)

#345000
1#
1)
b11111111111111110000000000000000 0
b100000 1

#350000
0#
0)

#355000
1#
1)
b11111111111111010000000000000000 0
b100001 1

#360000
0#
0)

#365000
1#
1)
b11111111111110100000000000000000 /
b11111111111110100000000000000000 0
b100010 1

#370000
0#
0)

#375000
1#
1)
b11111111111110010000000000000000 /
b11111111111110010000000000000000 0
b100011 1

#380000
0#
0)

#385000
1#
1)
b11111111111110110000000000000000 0
b100100 1

#390000
0#
0)

#395000
1#
1)
b11111111111111010000000000000000 0
b100101 1

#400000
0#
0)

#405000
1#
1)
b100110 1

#410000
0#
0)

#415000
1#
1)
b11111111111110110000000000000000 0
b100111 1

#420000
0#
0)

#425000
1#
1)
b11111111111111000000000000000000 0
b101000 1

#430000
0#
0)

#435000
1#
1)
b11111111111110000000000000000000 /
b11111111111110000000000000000000 0
b101001 1

#440000
0#
0)

#445000
1#
1)
b11111111111110110000000000000000 0
b101010 1

#450000
0#
0)

#455000
1#
1)
b11111111111101110000000000000000 /
b11111111111101110000000000000000 0
b101011 1

#460000
0#
0)

#465000
1#
1)
b11111111111110000000000000000000 0
b101100 1

#470000
0#
0)

#475000
1#
1)
b101101 1

#480000
0#
0)

#485000
1#
1)
b11111111111110100000000000000000 0
b101110 1

#490000
0#
0)

#495000
1#
1)
b11111111111101110000000000000000 0
b101111 1

#500000
0#
0)

#505000
1#
1)
b11111111111101010000000000000000 /
b11111111111101010000000000000000 0
b110000 1

#510000
0#
0)

#515000
1#
1)
b11111111111100110000000000000000 /
b11111111111100110000000000000000 0
b110001 1

#520000
0#
0)

#525000
1#
1)
b11111111111101010000000000000000 0
b110010 1

#530000
0#
0)

#535000
1#
1)
b11111111111101000000000000000000 0
b110011 1

#540000
0#
0)

#545000
1#
1)
b11111111111101010000000000000000 0
b110100 1

#550000
0#
0)

#555000
1#
1)
b11111111111101000000000000000000 0
b110101 1

#560000
0#
0)

#565000
1#
1)
b110110 1

#570000
0#
0)

#575000
1#
1)
b11111111111101100000000000000000 0
b110111 1

#580000
0#
0)

#585000
1#
1)
b11111111111101010000000000000000 0
b111000 1

#590000
0#
0)

#595000
1#
1)
b11111111111100110000000000000000 0
b111001 1

#600000
0#
0)

#605000
1#
1)
b11111111111100100000000000000000 /
b11111111111100100000000000000000 0
b111010 1

#610000
0#
0)

#615000
1#
1)
b11111111111101110000000000000000 0
b111011 1

#620000
0#
0)

#625000
1#
1)
b11111111111100110000000000000000 0
b111100 1

#630000
0#
0)

#635000
1#
1)
b11111111111101110000000000000000 0
b111101 1

#640000
0#
0)

#645000
1#
1)
b111110 1

#650000
0#
0)

#655000
1#
1)
b11111111111101000000000000000000 0
b111111 1

#660000
0#
0)

#665000
1#
1)
b11111111111100000000000000000000 /
b11111111111100000000000000000000 0
b1000000 1

#670000
0#
0)

#675000
1#
1)
b11111111111100100000000000000000 0
b1000001 1

#680000
0#
0)

#685000
1#
1)
b11111111111011010000000000000000 /
b11111111111011010000000000000000 0
b1000010 1

#690000
0#
0)

#695000
1#
1)
b11111111111100010000000000000000 0
b1000011 1

#700000
0#
0)

#705000
1#
1)
b11111111111100000000000000000000 0
b1000100 1

#710000
0#
0)

#715000
1#
1)
b11111111111100110000000000000000 0
b1000101 1

#720000
0#
0)

#725000
1#
1)
b11111111111100000000000000000000 0
b1000110 1

#730000
0#
0)

#735000
1#
1)
b11111111111100010000000000000000 0
b1000111 1

#740000
0#
0)

#745000
1#
1)
b11111111111100000000000000000000 0
b1001000 1

#750000
0#
0)

#755000
1#
1)
b1001001 1

#760000
0#
0)

#765000
1#
1)
b11111111111100100000000000000000 0
b1001010 1

#770000
0#
0)

#775000
1#
1)
b1001011 1

#780000
0#
0)

#785000
1#
1)
b11111111111011110000000000000000 0
b1001100 1

#790000
0#
0)

#795000
1#
1)
b11111111111011100000000000000000 0
b1001101 1

#800000
0#
0)

#805000
1#
1)
b11111111111100100000000000000000 0
b1001110 1

#810000
0#
0)

#815000
1#
1)
b11111111111100010000000000000000 0
b1001111 1

#820000
0#
0)

#825000
1#
1)
b11111111111010110000000000000000 /
b11111111111010110000000000000000 0
b1010000 1

#830000
0#
0)

#835000
1#
1)
b11111111111011010000000000000000 0
b1010001 1

#840000
0#
0)

#845000
1#
1)
b11111111111100010000000000000000 0
b1010010 1

#850000
0#
0)

#855000
1#
1)
b11111111111011010000000000000000 0
b1010011 1

#860000
0#
0)

#865000
1#
1)
b11111111111011100000000000000000 0
b1010100 1

#870000
0#
0)

#875000
1#
1)
b11111111111011000000000000000000 0
b1010101 1

#880000
0#
0)

#885000
1#
1)
b11111111111011110000000000000000 0
b1010110 1

#890000
0#
0)

#895000
1#
1)
b11111111111011010000000000000000 0
b1010111 1

#900000
0#
0)

#905000
1#
1)
b1011000 1

#910000
0#
0)

#915000
1#
1)
b11111111111010100000000000000000 /
b11111111111010100000000000000000 0
b1011001 1

#920000
0#
0)

#925000
1#
1)
b11111111111011010000000000000000 0
b1011010 1

#930000
0#
0)

#935000
1#
1)
b1011011 1

#940000
0#
0)

#945000
1#
1)
b11111111111010110000000000000000 0
b1011100 1

#950000
0#
0)

#955000
1#
1)
b11111111111010100000000000000000 0
b1011101 1

#960000
0#
0)

#965000
1#
1)
b11111111111010010000000000000000 /
b11111111111010010000000000000000 0
b1011110 1

#970000
0#
0)

#975000
1#
1)
b11111111111011000000000000000000 0
b1011111 1

#980000
0#
0)

#985000
1#
1)
b11111111111010010000000000000000 0
b1100000 1

#990000
0#
0)

#995000
1#
1)
b11111111111010100000000000000000 0
b1100001 1

#1000000
0#
0)

#1005000
1#
1)
b11111111111001010000000000000000 /
b11111111111001010000000000000000 0
b1100010 1

#1010000
0#
0)

#1015000
1#
1)
b11111111111010110000000000000000 0
b1100011 1

#1020000
0#
0)

#1025000
1#
1)
b11111111111010100000000000000000 0
b1100100 1

#1030000
0#
0)

#1035000
1#
1$
b1110000000000000000 %
b11111111111001010000000000000000 &
1)
1*
b1110000000000000000 +
b11111111111001010000000000000000 ,
b0 -
bx 0
b1100101 1

